README.md
setup.cfg
setup.py
trex_apis.egg-info/PKG-INFO
trex_apis.egg-info/SOURCES.txt
trex_apis.egg-info/dependency_links.txt
trex_apis.egg-info/requires.txt
trex_apis.egg-info/top_level.txt
trexapi/__init__.py
trexapi/conf.py
trexapi/controllers/__init__.py
trexapi/controllers/api_routes.py
trexapi/controllers/app_api_routes.py
trexapi/controllers/customer_api_routes.py
trexapi/controllers/customer_membership_api_routes.py
trexapi/controllers/customer_reward_api_routes.py
trexapi/controllers/device_util_api_routes.py
trexapi/controllers/loyalty_api_routes.py
trexapi/controllers/lucky_draw_api_routes.py
trexapi/controllers/merchant_api_routes.py
trexapi/controllers/message_api_routes.py
trexapi/controllers/outlet_api_routes.py
trexapi/controllers/outlet_report_api_routes.py
trexapi/controllers/payment_api_routes.py
trexapi/controllers/pos_api_routes.py
trexapi/controllers/prepaid_api_routes.py
trexapi/controllers/rating_api_routes.py
trexapi/controllers/redemption_api_routes.py
trexapi/controllers/reward_api_routes.py
trexapi/controllers/sales_api_routes.py
trexapi/controllers/support_api_routes.py
trexapi/controllers/transaction_api_routes.py
trexapi/controllers/user_api_routes.py
trexapi/controllers/user_reward_api_routes.py
trexapi/controllers/voucher_api_routes.py
trexapi/decorators/__init__.py
trexapi/decorators/api_decorators.py
trexapi/forms/__init__.py
trexapi/forms/customer_api_forms.py
trexapi/forms/reward_api_forms.py
trexapi/forms/sales_api_forms.py
trexapi/forms/user_api_forms.py
trexapi/libs/__init__.py
trexapi/libs/api_decorator.py
trexapi/libs/flask_auth_wrapper.py
trexapi/utils/__init__.py
trexapi/utils/api_helpers.py
trexapi/utils/push_notification_helper.py
trexapi/utils/redemption_catalogue_helper.py