Metadata-Version: 2.4
Name: trex_apis
Version: 1.7.3
Summary: TRex APIs package
Home-page: https://bitbucket.org/lokjac/trex-apis
Author: Jack Lok
Author-email: sglok77@gmail.com
Classifier: Programming Language :: Python :: 3
Classifier: License :: OSI Approved :: MIT License
Classifier: Operating System :: OS Independent
Requires-Dist: cryptography
Requires-Dist: basicauth
Requires-Dist: trex_conf
Requires-Dist: trex_model
Requires-Dist: trex_lib
Requires-Dist: trex_program
Dynamic: author
Dynamic: author-email
Dynamic: classifier
Dynamic: description
Dynamic: description-content-type
Dynamic: home-page
Dynamic: requires-dist
Dynamic: summary
